Metadata-Version: 2.1
Name: schnapsen-dev
Version: 0.0.4
Summary: A platform for coding and running card playing bots
Home-page: https://github.com/intelligent-systems-course/
Maintainer-email: nospam@nospam.com
Project-URL: Bug Tracker, https://github.com/intelligent-systems-course/
Classifier: Programming Language :: Python :: 3
Classifier: License :: OSI Approved :: GNU General Public License v3 or later (GPLv3+)
Classifier: Operating System :: OS Independent
Classifier: Development Status :: 1 - Planning
Classifier: Intended Audience :: Education
Classifier: Topic :: Games/Entertainment
Requires-Python: >=3.10
Provides-Extra: test
Provides-Extra: dev
License-File: LICENSE
